[
    {
        "app_id": "com.uploadedlobster.peek.desktop",
        "date_created": 1555628977.0,
        "description": "This crashed on me every time I tried to save a gif.",
        "distro": "Ubuntu",
        "karma_down": 0,
        "karma_up": 11,
        "locale": "en_US",
        "rating": 40,
        "reported": 0,
        "review_id": 22112,
        "score": 54,
        "summary": "BUGGY!",
        "user_display": "Joey",
        "user_hash": "16e770f797e07840e8a84293bf6485cf414aca44",
        "user_skey": "32ae49dcf2cb8f8bf2388a8b63c715c38a4117b6",
        "version": "1.3.1"
    },
    {
        "app_id": "com.uploadedlobster.peek.desktop",
        "date_created": 1615445173.0,
        "description": "Doesn't tell you that you can only record up to 5\nmins approx. Went to record my grandmother's \nfuneral. Stuck on \"Rendering\" I press \"stop\" I'll\nlose the recording altogether. Not looking good.",
        "distro": "Ubuntu",
        "karma_down": 0,
        "karma_up": 0,
        "locale": "en_US",
        "rating": 20,
        "reported": 0,
        "review_id": 350831,
        "score": 51,
        "summary": "Not impressive",
        "user_display": "Ralph",
        "user_hash": "2f057f91f1a9784c0060ccbf998df5dffbf8034f",
        "user_skey": "32ae49dcf2cb8f8bf2388a8b63c715c38a4117b6",
        "version": "1.5.1-1"
    },
    {
        "app_id": "com.uploadedlobster.peek.desktop",
        "date_created": 1617087649.0,
        "description": "Minimal & intuitive user interface. Simply great. ",
        "distro": "Ubuntu",
        "karma_down": 0,
        "karma_up": 0,
        "locale": "en_US.UTF-8",
        "rating": 100,
        "reported": 0,
        "review_id": 358481,
        "score": 41,
        "summary": "Really great app",
        "user_display": "Shenphen",
        "user_hash": "0c6ec0a6b305a6360537b3823211a6e5f2b5a60d",
        "user_skey": "32ae49dcf2cb8f8bf2388a8b63c715c38a4117b6",
        "version": "1.5.1"
    },
    {
        "app_id": "com.uploadedlobster.peek.desktop",
        "date_created": 1557421972.0,
        "description": "Crashes each time when saving GIF or APNG animation, after Ubuntu update to 19.04",
        "distro": "Ubuntu",
        "karma_down": 0,
        "karma_up": 5,
        "locale": "en_US",
        "rating": 60,
        "reported": 0,
        "review_id": 31496,
        "score": 36,
        "summary": "Problem :/",
        "user_display": "pacheco",
        "user_hash": "7d96efd577095f7aa3ed49d617cb0221b2d5176e",
        "user_skey": "32ae49dcf2cb8f8bf2388a8b63c715c38a4117b6",
        "version": "1.3.1"
    },
    {
        "app_id": "com.uploadedlobster.peek.desktop",
        "date_created": 1612863194.0,
        "description": "It works with XServer, but does not work with Wayland (as users are reporting that it crashes, most likely they are using Wayland).",
        "distro": "Ubuntu",
        "karma_down": 0,
        "karma_up": 0,
        "locale": "en_US.UTF-8",
        "rating": 60,
        "reported": 0,
        "review_id": 338710,
        "score": 33,
        "summary": "Nice, but does not work on Wayland",
        "user_display": "Pavol Rajzak",
        "user_hash": "dc29acabd9f3b892613aec732639d4889f1b2725",
        "user_skey": "32ae49dcf2cb8f8bf2388a8b63c715c38a4117b6",
        "version": "1.5.1"
    },
    {
        "app_id": "com.uploadedlobster.peek.desktop",
        "date_created": 1613919406.0,
        "description": "Didn't like the interface, it stops recording if I drag the recording dialog, Annoying.",
        "distro": "Ubuntu",
        "karma_down": 0,
        "karma_up": 0,
        "locale": "en_IN",
        "rating": 40,
        "reported": 0,
        "review_id": 343603,
        "score": 33,
        "summary": "UI Glitch",
        "user_display": "boontu",
        "user_hash": "15a1219b3c118584ddf8efe8bb6ed113d5113f96",
        "user_skey": "32ae49dcf2cb8f8bf2388a8b63c715c38a4117b6",
        "version": "1.5.1"
    },
    {
        "app_id": "com.uploadedlobster.peek.desktop",
        "date_created": 1615796395.0,
        "description": "Record only dark screen and mouse cursor, saves 2 minute video as 120kb.mp4",
        "distro": "Fedora",
        "karma_down": 0,
        "karma_up": 0,
        "locale": "en_US.UTF-8",
        "rating": 20,
        "reported": 0,
        "review_id": 352298,
        "score": 31,
        "summary": "Doesn't work on Fedora 33",
        "user_display": "Personal",
        "user_hash": "038630c0640ba5b53eccb8a94e72e383059c9cfe",
        "user_skey": "32ae49dcf2cb8f8bf2388a8b63c715c38a4117b6",
        "version": "1.5.1"
    },
    {
        "app_id": "com.uploadedlobster.peek",
        "date_created": 1617268014.0,
        "description": "Recorded for 10 minutes.\nAfter \"stop\", blocks forever and the cached file has only 5 minutes.",
        "distro": "Fedora",
        "karma_down": 0,
        "karma_up": 0,
        "locale": "en_US.UTF-8",
        "rating": 20,
        "reported": 0,
        "review_id": 359342,
        "score": 31,
        "summary": "bad",
        "user_display": "GOU Lingfeng",
        "user_hash": "f2fc63f489d1c7c4533691c538e8f4cdd8437de3",
        "user_skey": "32ae49dcf2cb8f8bf2388a8b63c715c38a4117b6",
        "version": "1.5.1"
    },
    {
        "app_id": "com.uploadedlobster.peek.desktop",
        "date_created": 1519871367.0,
        "description": "One star lost per flaw. The first is the error \"Could not start recording, already an active recording using org.gnome.Shell.Screencast?\" when trying to record .mp4 files. This is apparently a known issue, so whatever.\n\nThe second is that if you move the recording window while recording, the recording stops and does not appear to be saved. Only lost about 10 minutes of work, but still should not happen.",
        "distro": "Fedora",
        "karma_down": 0,
        "karma_up": 11,
        "locale": "en_US",
        "rating": 60,
        "reported": 0,
        "review_id": 6621,
        "score": 24,
        "summary": "Decent recorder, two huge flaws",
        "user_display": "Will Nilges",
        "user_hash": "fedb41b1d2b441c55bb1797ec3e685f44bebc642",
        "user_skey": "32ae49dcf2cb8f8bf2388a8b63c715c38a4117b6",
        "version": "1.2.2"
    },
    {
        "app_id": "com.uploadedlobster.peek.desktop",
        "date_created": 1609897912.0,
        "description": "Thank you for this great app. It just works. No glitches ",
        "distro": "Ubuntu",
        "karma_down": 0,
        "karma_up": 0,
        "locale": "en_IN",
        "rating": 100,
        "reported": 0,
        "review_id": 324750,
        "score": 24,
        "summary": "Great App!",
        "user_display": "Kader Mohideen Fasid",
        "user_hash": "2820588290001e82da97271eb43d079d158caaf3",
        "user_skey": "32ae49dcf2cb8f8bf2388a8b63c715c38a4117b6",
        "version": "1.5.1"
    },
    {
        "app_id": "com.uploadedlobster.peek.desktop",
        "date_created": 1611038433.0,
        "description": "its really simple app. Does exactly as described.\n\ndoes not record sound and it is already mentioned in the description so no complaints.",
        "distro": "Ubuntu",
        "karma_down": 0,
        "karma_up": 0,
        "locale": "en_US.UTF-8",
        "rating": 100,
        "reported": 0,
        "review_id": 329886,
        "score": 24,
        "summary": "Easy to use Great app",
        "user_display": "Iqbal Sajid",
        "user_hash": "1d4235dc6ddf0f15d08c1fb01202b969fcc5043e",
        "user_skey": "32ae49dcf2cb8f8bf2388a8b63c715c38a4117b6",
        "version": "1.5.1"
    },
    {
        "app_id": "com.uploadedlobster.peek.desktop",
        "date_created": 1611230427.0,
        "description": "The best free app for recording gifs on Linux",
        "distro": "Ubuntu",
        "karma_down": 0,
        "karma_up": 0,
        "locale": "en_US.UTF-8",
        "rating": 100,
        "reported": 0,
        "review_id": 330861,
        "score": 24,
        "summary": "Great app",
        "user_display": "NA",
        "user_hash": "bebcb71ba16a7df9e4f05c791687942f69b09c13",
        "user_skey": "32ae49dcf2cb8f8bf2388a8b63c715c38a4117b6",
        "version": "1.5.1"
    },
    {
        "app_id": "com.uploadedlobster.peek.desktop",
        "date_created": 1611767762.0,
        "description": "Crashes every time I attempt to launch.",
        "distro": "Ubuntu",
        "karma_down": 0,
        "karma_up": 0,
        "locale": "en_US.UTF-8",
        "rating": 40,
        "reported": 0,
        "review_id": 333480,
        "score": 24,
        "summary": "Doesn't launch on Ubunut 20.04",
        "user_display": "Chris Hayes",
        "user_hash": "fd78cad0930dc4ab6ea6ae99cb89b971d7b3486c",
        "user_skey": "32ae49dcf2cb8f8bf2388a8b63c715c38a4117b6",
        "version": "1.5.1"
    },
    {
        "app_id": "com.uploadedlobster.peek.desktop",
        "date_created": 1556112969.0,
        "description": "Crashes each time when saving GIF or APNG animation, after Ubuntu update to 19.04 version today (24-04-2019).\n\nIs it possible to do something ?\n\nThanks ",
        "distro": "Ubuntu",
        "karma_down": 0,
        "karma_up": 3,
        "locale": "en_US",
        "rating": 40,
        "reported": 0,
        "review_id": 24692,
        "score": 23,
        "summary": "Crashes when saving GIF or APNG animation",
        "user_display": "Andr\u00e9",
        "user_hash": "c4e7e42da747ec5727c5eeea98184bae3d45ec46",
        "user_skey": "32ae49dcf2cb8f8bf2388a8b63c715c38a4117b6",
        "version": "1.3.1"
    },
    {
        "app_id": "com.uploadedlobster.peek.desktop",
        "date_created": 1612444252.0,
        "description": "it works very well, and super intuitive, just perfect",
        "distro": "Debian GNU/Linux",
        "karma_down": 0,
        "karma_up": 0,
        "locale": "en_US",
        "rating": 100,
        "reported": 0,
        "review_id": 336731,
        "score": 23,
        "summary": "just perfect",
        "user_display": "rekard0",
        "user_hash": "03ceb256bfc73fd15dc77939556bd35cc5c2fb17",
        "user_skey": "32ae49dcf2cb8f8bf2388a8b63c715c38a4117b6",
        "version": "1.3.1"
    },
    {
        "app_id": "com.uploadedlobster.peek.desktop",
        "date_created": 1613446945.0,
        "description": "This is a bummer, I believe there's a lot of potential for this app",
        "distro": "Fedora",
        "karma_down": 0,
        "karma_up": 0,
        "locale": "en_US.UTF-8",
        "rating": 40,
        "reported": 0,
        "review_id": 341441,
        "score": 23,
        "summary": "Doesn't work well with wayland, and doesn't record audio",
        "user_display": "Khalil SLEIMI",
        "user_hash": "3e711cce55f162daeb1d816455e18964bfbc4035",
        "user_skey": "32ae49dcf2cb8f8bf2388a8b63c715c38a4117b6",
        "version": "1.5.1"
    },
    {
        "app_id": "com.uploadedlobster.peek",
        "date_created": 1613371871.0,
        "description": "why doesnt it record sound of the video???\nwithout sound it is all useless\ndoes someone knows how to work correctly with it???",
        "distro": "Endless",
        "karma_down": 0,
        "karma_up": 0,
        "locale": "en_US.utf8",
        "rating": 20,
        "reported": 0,
        "review_id": 341146,
        "score": 23,
        "summary": "a question",
        "user_display": "keshavarz",
        "user_hash": "e28719e55efa121b40743f03c3eb70b33aae8917",
        "user_skey": "32ae49dcf2cb8f8bf2388a8b63c715c38a4117b6",
        "version": "1.5.1"
    },
    {
        "app_id": "com.uploadedlobster.peek.desktop",
        "date_created": 1611505750.0,
        "description": "i can't save a video to a folder on a second hard drive, bc peek's flatpak version simply doesn't detect it.\nim back on AUR version.",
        "distro": "Manjaro Linux",
        "karma_down": 0,
        "karma_up": 0,
        "locale": "en_US",
        "rating": 20,
        "reported": 0,
        "review_id": 332163,
        "score": 14,
        "summary": "flatpak version is horrible",
        "user_display": "sb",
        "user_hash": "9407cead0d9dd05960b96f439d34816a2462a6f1",
        "user_skey": "32ae49dcf2cb8f8bf2388a8b63c715c38a4117b6",
        "version": "stable"
    },
    {
        "app_id": "com.uploadedlobster.peek.desktop",
        "date_created": 1501000377.0,
        "description": "If it can record the whole screen then it'll be perfect!",
        "distro": "Antergos",
        "karma_down": 0,
        "karma_up": 3,
        "locale": "en_US",
        "rating": 100,
        "reported": 0,
        "review_id": 4050,
        "score": 0,
        "summary": "Great app",
        "user_display": "khai",
        "user_hash": "68368c06917ccc51591872309ef7627d7eb92114",
        "user_skey": "32ae49dcf2cb8f8bf2388a8b63c715c38a4117b6",
        "version": "1.0.3"
    },
    {
        "app_id": "com.uploadedlobster.peek.desktop",
        "date_created": 1508502213.0,
        "description": "Allow save what I'm seeing so others devs can see it too.",
        "distro": "Fedora",
        "karma_down": 0,
        "karma_up": 2,
        "locale": "en_US",
        "rating": 100,
        "reported": 0,
        "review_id": 5066,
        "score": 0,
        "summary": "Excellent to share bug reports",
        "user_display": "Marcelo Andrade R",
        "user_hash": "81c989385b038ce8cec124239e52eb9f4a3a3c78",
        "user_skey": "32ae49dcf2cb8f8bf2388a8b63c715c38a4117b6",
        "version": "stable"
    }
]